pytrilogyt-0.0.21.dist-info/licenses/LICENSE.md
trilogyt/__init__.py
trilogyt/constants.py
trilogyt/core.py
trilogyt/core_v2.py
trilogyt/enums.py
trilogyt/exceptions.py
trilogyt/fingerprint.py
trilogyt/graph.py
trilogyt/helpers.py
trilogyt/io.py
trilogyt/models.py
trilogyt/dagster/__init__.py
trilogyt/dagster/config.py
trilogyt/dagster/constants.py
trilogyt/dagster/generate.py
trilogyt/dagster/run.py
trilogyt/dbt/__init__.py
trilogyt/dbt/config.py
trilogyt/dbt/generate.py
trilogyt/dbt/run.py
trilogyt/native/__init__.py
trilogyt/native/generate.py
trilogyt/native/run.py
trilogyt/scripts/__init__.py
trilogyt/scripts/core.py
trilogyt/scripts/dagster.py
trilogyt/scripts/dbt.py
trilogyt/scripts/main.py
trilogyt/scripts/native.py
pytrilogyt-0.0.21.dist-info/METADATA
pytrilogyt-0.0.21.dist-info/WHEEL
pytrilogyt-0.0.21.dist-info/entry_points.txt
pytrilogyt-0.0.21.dist-info/top_level.txt
pytrilogyt-0.0.21.dist-info/RECORD
