Metadata-Version: 2.4
Name: pytrilogyt
Version: 0.0.21
Summary: Enhanced Trilogy for common ETL needs.
Home-page: 
Author: 
Author-email: preql-community@gmail.com
Classifier: Programming Language :: Python
Classifier: Programming Language :: Python :: 3
Classifier: Programming Language :: Python :: 3.9
Classifier: Programming Language :: Python :: 3.10
Classifier: Programming Language :: Python :: 3.11
Classifier: Programming Language :: Python :: 3.12
Classifier: Programming Language :: Python :: 3.13
License-File: LICENSE.md
Requires-Dist: pytrilogy>=0.3.142
Requires-Dist: dbt-core
Provides-Extra: bigquery
Requires-Dist: dbt-bigquery; extra == "bigquery"
Provides-Extra: duckdb
Requires-Dist: dbt-duckdb; extra == "duckdb"
Provides-Extra: dagster
Requires-Dist: dagster; extra == "dagster"
Requires-Dist: dagster-duckdb; extra == "dagster"
Dynamic: author-email
Dynamic: classifier
Dynamic: description
Dynamic: description-content-type
Dynamic: license-file
Dynamic: provides-extra
Dynamic: requires-dist
Dynamic: summary
